README.md
copycat3
copycat3.py
setup.py
copycat_clipboard3.egg-info/PKG-INFO
copycat_clipboard3.egg-info/SOURCES.txt
copycat_clipboard3.egg-info/dependency_links.txt
copycat_clipboard3.egg-info/requires.txt
copycat_clipboard3.egg-info/top_level.txt