Metadata-Version: 1.0
Name: copycat-clipboard3
Version: 1.1
Summary: easy way let use clip on command line with system clip (support python 3)
Home-page: https://github.com/iwdmb/copycat
Author: Ming
Author-email: ming@alone.tw
License: MIT
Platform: UNKNOWN
